xiaobo_task/__init__.py
xiaobo_task/domain.py
xiaobo_task/exceptions.py
xiaobo_task/facade.py
xiaobo_task/manager.py
xiaobo_task/proxy_pool.py
xiaobo_task/settings.py
xiaobo_task/util.py
xiaobo_task-1.0.6.dist-info/METADATA
xiaobo_task-1.0.6.dist-info/WHEEL
xiaobo_task-1.0.6.dist-info/RECORD
