Metadata-Version: 2.4
Name: xiaobo-task
Version: 1.0.6
Summary: 自用多线程任务模块
Author-email: xiaobo <tb791549729@gmail.com>
Requires-Python: >=3.10
Requires-Dist: curl-cffi>=0.13.0
Requires-Dist: loguru>=0.7.3
Requires-Dist: pydantic-settings>=2.12.0
Requires-Dist: python-dotenv>=1.2.1
Requires-Dist: tenacity>=9.1.2
